fuse/__init__.py
fuse/common.py
fuse/context.py
fuse/context_utils.py
fuse/dtypes.py
fuse/plugin.py
fuse/plugins/__init__.py
fuse/plugins/detector_physics/README.md
fuse/plugins/detector_physics/__init__.py
fuse/plugins/detector_physics/csv_input.py
fuse/plugins/detector_physics/delayed_electrons/__init__.py
fuse/plugins/detector_physics/delayed_electrons/delayed_electrons_drift.py
fuse/plugins/detector_physics/delayed_electrons/delayed_electrons_extraction.py
fuse/plugins/detector_physics/delayed_electrons/delayed_electrons_merger.py
fuse/plugins/detector_physics/delayed_electrons/delayed_electrons_propagation.py
fuse/plugins/detector_physics/delayed_electrons/delayed_electrons_s1photonhits.py
fuse/plugins/detector_physics/delayed_electrons/delayed_electrons_secondary_scintillation.py
fuse/plugins/detector_physics/delayed_electrons/photo_ionization_electrons.py
fuse/plugins/detector_physics/electron_drift.py
fuse/plugins/detector_physics/electron_extraction.py
fuse/plugins/detector_physics/electron_propagation.py
fuse/plugins/detector_physics/s1_photon_hits.py
fuse/plugins/detector_physics/s1_photon_propagation.py
fuse/plugins/detector_physics/s2_photon_propagation.py
fuse/plugins/detector_physics/secondary_scintillation.py
fuse/plugins/micro_physics/README.md
fuse/plugins/micro_physics/__init__.py
fuse/plugins/micro_physics/cuts_and_selections/__init__.py
fuse/plugins/micro_physics/cuts_and_selections/apply_selections.py
fuse/plugins/micro_physics/cuts_and_selections/detector_volumes.py
fuse/plugins/micro_physics/cuts_and_selections/physics_cases.py
fuse/plugins/micro_physics/electric_field.py
fuse/plugins/micro_physics/find_cluster.py
fuse/plugins/micro_physics/input.py
fuse/plugins/micro_physics/lineage_cluster.py
fuse/plugins/micro_physics/merge_cluster.py
fuse/plugins/micro_physics/merge_lineage.py
fuse/plugins/micro_physics/microphysics_summary.py
fuse/plugins/micro_physics/volume_properties.py
fuse/plugins/micro_physics/yields.py
xenon_fuse-1.6.3.dist-info/METADATA
xenon_fuse-1.6.3.dist-info/WHEEL
xenon_fuse-1.6.3.dist-info/licenses/LICENSE
xenon_fuse-1.6.3.dist-info/RECORD
