Metadata-Version: 2.4
Name: xenon-fuse
Version: 1.6.3
Summary: XENON Framework for Unified Simulations of Events
License-File: LICENSE
Author: Henning Schulze Eißing,
Author-email: h_schu55@uni-muenster.de
Requires-Python: >=3.9,<4.0
Classifier: Development Status :: 3 - Alpha
Classifier: Intended Audience :: Science/Research
Classifier: Natural Language :: English
Classifier: Operating System :: OS Independent
Classifier: Programming Language :: Python :: 3
Classifier: Programming Language :: Python :: 3.9
Classifier: Programming Language :: Python :: 3.10
Classifier: Programming Language :: Python :: 3.11
Classifier: Programming Language :: Python :: 3.12
Classifier: Programming Language :: Python :: 3.13
Classifier: Programming Language :: Python :: 3.14
Classifier: Programming Language :: Python :: Implementation :: CPython
Classifier: Topic :: Scientific/Engineering :: Physics
Requires-Dist: awkward (>=2.5.1)
Requires-Dist: immutabledict
Requires-Dist: nestpy (>=2.0.2)
Requires-Dist: numba (>=0.58.1)
Requires-Dist: numpy
Requires-Dist: pandas
Requires-Dist: periodictable
Requires-Dist: scikit-learn
Requires-Dist: scipy
Requires-Dist: strax (>=1.6.0)
Requires-Dist: straxen (>=2.2.3)
Requires-Dist: timeout_decorator
Requires-Dist: uproot (>=5.2.1)
Requires-Dist: utilix (>=0.11.0)
Project-URL: Homepage, https://github.com/XENONnT/fuse
